{
  "0": "accordion", 
  "1": "airplane", 
  "2": "ant", 
  "3": "antelope", 
  "4": "apple", 
  "5": "armadillo", 
  "6": "artichoke", 
  "7": "axe", 
  "8": "baby", 
  "9": "backpack", 
  "10": "bagel", 
  "11": "balance", 
  "12": "banana", 
  "13": "band", 
  "14": "banjo", 
  "15": "baseball", 
  "16": "basketball", 
  "17": "bathing", 
  "18": "beaker", 
  "19": "bear", 
  "20": "bee", 
  "21": "bell", 
  "22": "bench", 
  "23": "bicycle", 
  "24": "binder", 
  "25": "bird", 
  "26": "bookshelf", 
  "27": "bow", 
  "28": "bow", 
  "29": "bowl", 
  "30": "brassiere", 
  "31": "burrito", 
  "32": "bus", 
  "33": "butterfly", 
  "34": "camel", 
  "35": "can", 
  "36": "car", 
  "37": "cart", 
  "38": "cattle", 
  "39": "cello", 
  "40": "centipede", 
  "41": "chain", 
  "42": "chair", 
  "43": "chime", 
  "44": "cocktail", 
  "45": "coffee", 
  "46": "computer", 
  "47": "computer", 
  "48": "corkscrew", 
  "49": "cream", 
  "50": "croquet", 
  "51": "crutch", 
  "52": "cucumber", 
  "53": "cup", 
  "54": "diaper", 
  "55": "digital", 
  "56": "dishwasher", 
  "57": "dog", 
  "58": "domestic", 
  "59": "dragonfly", 
  "60": "drum", 
  "61": "dumbbell", 
  "62": "electric", 
  "63": "elephant", 
  "64": "face", 
  "65": "fig", 
  "66": "filing", 
  "67": "flower", 
  "68": "flute", 
  "69": "fox", 
  "70": "french", 
  "71": "frog", 
  "72": "frying", 
  "73": "giant", 
  "74": "goldfish", 
  "75": "golf", 
  "76": "golfcart", 
  "77": "guacamole", 
  "78": "guitar", 
  "79": "hair", 
  "80": "hair", 
  "81": "hamburger", 
  "82": "hammer", 
  "83": "hamster", 
  "84": "harmonica", 
  "85": "harp", 
  "86": "hat", 
  "87": "head", 
  "88": "helmet", 
  "89": "hippopotamus", 
  "90": "horizontal", 
  "91": "horse", 
  "92": "hotdog", 
  "93": "iPod", 
  "94": "isopod", 
  "95": "jellyfish", 
  "96": "koala", 
  "97": "ladle", 
  "98": "ladybug", 
  "99": "lamp", 
  "100": "laptop", 
  "101": "lemon", 
  "102": "lion", 
  "103": "lipstick", 
  "104": "lizard", 
  "105": "lobster", 
  "106": "maillot", 
  "107": "maraca", 
  "108": "microphone", 
  "109": "microwave", 
  "110": "milk", 
  "111": "miniskirt", 
  "112": "monkey", 
  "113": "motorcycle", 
  "114": "mushroom", 
  "115": "nail", 
  "116": "neck", 
  "117": "oboe", 
  "118": "orange", 
  "119": "otter", 
  "120": "pencil", 
  "121": "pencil", 
  "122": "perfume", 
  "123": "person", 
  "124": "piano", 
  "125": "pineapple", 
  "126": "ping-pong", 
  "127": "pitcher", 
  "128": "pizza", 
  "129": "plastic", 
  "130": "plate", 
  "131": "pomegranate", 
  "132": "popsicle", 
  "133": "porcupine", 
  "134": "power", 
  "135": "pretzel", 
  "136": "printer", 
  "137": "puck", 
  "138": "punching", 
  "139": "purse", 
  "140": "rabbit", 
  "141": "racket", 
  "142": "ray", 
  "143": "red", 
  "144": "refrigerator", 
  "145": "remote", 
  "146": "rubber", 
  "147": "rugby", 
  "148": "ruler", 
  "149": "salt", 
  "150": "saxophone", 
  "151": "scorpion", 
  "152": "screwdriver", 
  "153": "seal", 
  "154": "sheep", 
  "155": "ski", 
  "156": "skunk", 
  "157": "snail", 
  "158": "snake", 
  "159": "snowmobile", 
  "160": "snowplow", 
  "161": "soap", 
  "162": "soccer", 
  "163": "sofa", 
  "164": "spatula", 
  "165": "squirrel", 
  "166": "starfish", 
  "167": "stethoscope", 
  "168": "stove", 
  "169": "strainer", 
  "170": "strawberry", 
  "171": "stretcher", 
  "172": "sunglasses", 
  "173": "swimming", 
  "174": "swine", 
  "175": "syringe", 
  "176": "table", 
  "177": "tape", 
  "178": "tennis", 
  "179": "tick", 
  "180": "tie", 
  "181": "tiger", 
  "182": "toaster", 
  "183": "traffic", 
  "184": "train", 
  "185": "trombone", 
  "186": "trumpet", 
  "187": "turtle", 
  "188": "tv", 
  "189": "unicycle", 
  "190": "vacuum", 
  "191": "violin", 
  "192": "volleyball", 
  "193": "waffle", 
  "194": "washer", 
  "195": "water", 
  "196": "watercraft", 
  "197": "whale", 
  "198": "wine", 
  "199": "zebra"
}